{
    "_326": {
        "id": "326",
        "title_cn": "名侦探柯南",
        "title_jp": "名探偵コナン",
        "tips": "1996年1月8日 / こだま兼嗣（#1-#118）→山本泰一郎（#119-#332）→佐藤真人（#162、#219、#333-#504）→於地紘仁（#505-#666）→山本泰一郎（#667-#677）→於地紘仁（#678-#679）→山本泰一郎（#680-#974）→山本泰一郎、鎌仲史陽（#975-） / 青山剛昌 / 須藤昌朋(#1 -#355)→とみながまり(#219、#263、#356 - #504)→須藤昌朋、山中純子(#505-#576)→須藤昌朋(#577-#626)→須藤昌朋、牟田清司(#627-#680)→須藤昌朋(#681-#803)→須藤昌朋、岩井伸之(#804-#870) →須藤昌朋(#871-)",
        "stars": 7.7,
        "people": 6185,
        "year": 1996,
        "path": "cover/1996/名侦探柯南"
    },
    "_334": {
        "id": "334",
        "title_cn": "四驱兄弟",
        "title_jp": "爆走兄弟レッツ&ゴー!!",
        "tips": "51话 /  1996年1月8日 / 越田哲弘",
        "stars": 7.2,
        "people": 1799,
        "year": 1996,
        "path": "cover/1996/四驱兄弟"
    },
    "_312": {
        "id": "312",
        "title_cn": "浪客剑心",
        "title_jp": "るろうに剣心 -明治剣客浪漫譚-",
        "tips": "95话 /  1996年1月10日 / 古橋一浩 / 和月伸宏 / 濱洲英喜→室井ふみえ",
        "stars": 7.7,
        "people": 1658,
        "year": 1996,
        "path": "cover/1996/浪客剑心"
    },
    "_332": {
        "id": "332",
        "title_cn": "机动战舰抚子号",
        "title_jp": "機動戦艦ナデシコ",
        "tips": "26话 /  1996年10月1日 / 後藤圭二",
        "stars": 8.0,
        "people": 1191,
        "year": 1996,
        "path": "cover/1996/机动战舰抚子号"
    },
    "_318": {
        "id": "318",
        "title_cn": "秀逗魔导士NEXT",
        "title_jp": "スレイヤーズNEXT",
        "tips": "26话 /  1996年4月5日 / 渡部高志 / 神坂一 / 宮田奈保美",
        "stars": 7.9,
        "people": 952,
        "year": 1996,
        "path": "cover/1996/秀逗魔导士NEXT"
    },
    "_320": {
        "id": "320",
        "title_cn": "龙珠GT",
        "title_jp": "ドラゴンボールGT",
        "tips": "64话 /  1996年2月7日 / 鳥山明 / 中鶴勝祥",
        "stars": 7.2,
        "people": 938,
        "year": 1996,
        "path": "cover/1996/龙珠GT"
    },
    "_339": {
        "id": "339",
        "title_cn": "逮捕令",
        "title_jp": "逮捕しちゃうぞ",
        "tips": "51话 /  1996年10月5日 / わたなべひろし(～30話)、西村純二(31話～) / 藤島康介（讲谈社刊“パーティーKC”所载） / 中嶋敦子",
        "stars": 7.6,
        "people": 897,
        "year": 1996,
        "path": "cover/1996/逮捕令"
    },
    "_333": {
        "id": "333",
        "title_cn": "机动新世纪高达X",
        "title_jp": "機動新世紀ガンダムX",
        "tips": "39话 /  1996年4月5日 / 高松信司 / 矢立肇、富野由悠季 / 西村誠芳",
        "stars": 6.8,
        "people": 546,
        "year": 1996,
        "path": "cover/1996/机动新世纪高达X"
    },
    "_294": {
        "id": "294",
        "title_cn": "钢铁神兵B'T-X",
        "title_jp": "B'T-X",
        "tips": "25话 /  1996年4月6日 / 浜津守 / 車田正美 / 井上栄作、本桥秀之",
        "stars": 7.3,
        "people": 540,
        "year": 1996,
        "path": "cover/1996/钢铁神兵B'T-X"
    },
    "_295": {
        "id": "295",
        "title_cn": "超能勇士",
        "title_jp": "Beast Wars: Transformers",
        "tips": "52话 /  1996年9月16日",
        "stars": 7.5,
        "people": 394,
        "year": 1996,
        "path": "cover/1996/超能勇士"
    },
    "_336": {
        "id": "336",
        "title_cn": "美少女战士Sailor Stars",
        "title_jp": "美少女戦士セーラームーンセーラースターズ",
        "tips": "34话 /  1996-03-09 / 五十嵐卓哉 / 武内直子 / 爲我井克美",
        "stars": 7.4,
        "people": 319,
        "year": 1996,
        "path": "cover/1996/美少女战士Sailor Stars"
    },
    "_6672": {
        "id": "6672",
        "title_cn": "大雄与银河超特急",
        "title_jp": "ドラえもん のび太と銀河超特急",
        "tips": "1话 /  1996年3月2日",
        "stars": 7.2,
        "people": 232,
        "year": 1996,
        "path": "cover/1996/大雄与银河超特急"
    },
    "_6665": {
        "id": "6665",
        "title_cn": "X战记",
        "title_jp": "X -エックス-",
        "tips": "1话 /  1996年8月3日 / りんたろう / CLAMP / 結城信輝",
        "stars": 6.4,
        "people": 213,
        "year": 1996,
        "path": "cover/1996/X战记"
    },
    "_313": {
        "id": "313",
        "title_cn": "贤治之春",
        "title_jp": "イーハトーブ幻想〜KENjIの春",
        "tips": "1话 /  1996-12-14",
        "stars": 7.6,
        "people": 201,
        "year": 1996,
        "path": "cover/1996/贤治之春"
    },
    "_329": {
        "id": "329",
        "title_cn": "天空之艾斯嘉科尼",
        "title_jp": "天空のエスカフローネ",
        "tips": "26话 /  1996年4月2日 / 赤根和樹 / 矢立肇､河森正治 / 結城信輝",
        "stars": 7.0,
        "people": 186,
        "year": 1996,
        "path": "cover/1996/天空之艾斯嘉科尼"
    },
    "_308": {
        "id": "308",
        "title_cn": "玩偶游戏",
        "title_jp": "こどものおもちゃ",
        "tips": "102话 /  1996年4月5日 / 大地丙太郎 / 小花美穂",
        "stars": 7.5,
        "people": 186,
        "year": 1996,
        "path": "cover/1996/玩偶游戏"
    },
    "_307": {
        "id": "307",
        "title_cn": "乌龙派出所",
        "title_jp": "こちら葛飾区亀有公園前派出所",
        "tips": "373话 /  1996年6月16日 / やすみ哲夫→三沢伸→高松信司→高本宣弘→鴫野彰",
        "stars": 8.1,
        "people": 168,
        "year": 1996,
        "path": "cover/1996/乌龙派出所"
    },
    "_328": {
        "id": "328",
        "title_cn": "大草原上的小老鼠",
        "title_jp": "大草原上的小老鼠",
        "tips": "52话 /  1996",
        "stars": 6.5,
        "people": 167,
        "year": 1996,
        "path": "cover/1996/大草原上的小老鼠"
    },
    "_6669": {
        "id": "6669",
        "title_cn": "蜡笔小新 奇异乐园大冒险",
        "title_jp": "クレヨンしんちゃん ヘンダーランドの大冒険",
        "tips": "1话 /  1996-04-13 / 本郷みつる / 臼井儀人 / 原勝徳",
        "stars": 7.0,
        "people": 156,
        "year": 1996,
        "path": "cover/1996/蜡笔小新 奇异乐园大冒险"
    },
    "_6676": {
        "id": "6676",
        "title_cn": "怪医黑杰克 剧场版",
        "title_jp": "ブラック・ジャック 劇場版",
        "tips": "1话 /  1996年11月30日",
        "stars": 7.5,
        "people": 153,
        "year": 1996,
        "path": "cover/1996/怪医黑杰克 剧场版"
    },
    "_341": {
        "id": "341",
        "title_cn": "魔法少女砂沙美",
        "title_jp": "魔法少女プリティサミー",
        "tips": "26话 /  1996-10-04",
        "stars": 6.8,
        "people": 122,
        "year": 1996,
        "path": "cover/1996/魔法少女砂沙美"
    },
    "_6680": {
        "id": "6680",
        "title_cn": "秀逗魔导士RETURN",
        "title_jp": "劇場版 スレイヤーズRETURN",
        "tips": "1话 /  1996年8月3日",
        "stars": 7.0,
        "people": 105,
        "year": 1996,
        "path": "cover/1996/秀逗魔导士RETURN"
    },
    "_6674": {
        "id": "6674",
        "title_cn": "龙珠 最强之道",
        "title_jp": "ドラゴンボール 最強への道",
        "tips": "1话 /  1996年3月2日",
        "stars": 6.7,
        "people": 105,
        "year": 1996,
        "path": "cover/1996/龙珠 最强之道"
    },
    "_331": {
        "id": "331",
        "title_cn": "佐罗的传说",
        "title_jp": "快傑ゾロ",
        "tips": "52话 /  1996年4月5日 / 箕ノ口克己 / Johnston McCulley / 高谷浩利",
        "stars": 6.9,
        "people": 102,
        "year": 1996,
        "path": "cover/1996/佐罗的传说"
    },
    "_6675": {
        "id": "6675",
        "title_cn": "哆啦美与哆啦A梦七小子 机器人学校七不思议",
        "title_jp": "ドラミ&ドラえもんズ ロボット学校七不思議!?",
        "tips": "1话 /  1996年3月2日",
        "stars": 7.2,
        "people": 99,
        "year": 1996,
        "path": "cover/1996/哆啦美与哆啦A梦七小子 机器人学校七不思议"
    },
    "_6684": {
        "id": "6684",
        "title_cn": "金田一少年之事件簿 歌剧院杀人事件",
        "title_jp": "金田一少年の事件簿",
        "tips": "1话 /  1996年12月14日",
        "stars": 7.4,
        "people": 98,
        "year": 1996,
        "path": "cover/1996/金田一少年之事件簿 歌剧院杀人事件"
    },
    "_6683": {
        "id": "6683",
        "title_cn": "橙路 那个夏天的开始",
        "title_jp": "新きまぐれオレンジ☆ロード ～ そして、あの夏のはじまり",
        "tips": "1话 /  1996年11月2日 / 湯山邦彦 / まつもと泉、寺田憲史",
        "stars": 7.0,
        "people": 98,
        "year": 1996,
        "path": "cover/1996/橙路 那个夏天的开始"
    },
    "_6679": {
        "id": "6679",
        "title_cn": "鲁邦三世：DEAD OR ALIVE",
        "title_jp": "ルパン三世 DEAD OR ALIVE",
        "tips": "1话 /  1996年4月20日",
        "stars": 7.1,
        "people": 97,
        "year": 1996,
        "path": "cover/1996/鲁邦三世：DEAD OR ALIVE"
    },
    "_327": {
        "id": "327",
        "title_cn": "地狱老师",
        "title_jp": "地獄先生ぬ〜べ〜",
        "tips": "49话 /  1996年4月13日",
        "stars": 7.1,
        "people": 95,
        "year": 1996,
        "path": "cover/1996/地狱老师"
    },
    "_319": {
        "id": "319",
        "title_cn": "机械女神J",
        "title_jp": "セイバーマリオネットJ",
        "tips": "25话 /  1996年10月1日 / 下田正美 / あかほりさとる / 島村秀一",
        "stars": 7.1,
        "people": 88,
        "year": 1996,
        "path": "cover/1996/机械女神J"
    },
    "_309": {
        "id": "309",
        "title_cn": "山林小猎人",
        "title_jp": "はじめ人間ゴン",
        "tips": "39话 /  1996年4月3日 / 香川豊 / そのやましゅんじ / 岸義之",
        "stars": 6.6,
        "people": 85,
        "year": 1996,
        "path": "cover/1996/山林小猎人"
    },
    "_296": {
        "id": "296",
        "title_cn": "德克斯特的实验室 第一季",
        "title_jp": "Dexter's Laboratory Season 1",
        "tips": "13话 /  1996-04-28",
        "stars": 7.5,
        "people": 63,
        "year": 1996,
        "path": "cover/1996/德克斯特的实验室 第一季"
    },
    "_324": {
        "id": "324",
        "title_cn": "鲁邦三世 暮色双子星座的秘密",
        "title_jp": "ルパン三世 トワイライト☆ジェミニの秘密",
        "tips": "1话 /  1996年8月2日",
        "stars": 7.0,
        "people": 58,
        "year": 1996,
        "path": "cover/1996/鲁邦三世 暮色双子星座的秘密"
    },
    "_6682": {
        "id": "6682",
        "title_cn": "天地无用! in LOVE",
        "title_jp": "天地無用! in LOVE",
        "tips": "1话 /  1996年4月20日",
        "stars": 6.8,
        "people": 50,
        "year": 1996,
        "path": "cover/1996/天地无用! in LOVE"
    },
    "_315": {
        "id": "315",
        "title_cn": "奥运高手",
        "title_jp": "ガンバリスト! 駿",
        "tips": "30话 /  1996年7月1日 / 龟垣一 / 森末慎二",
        "stars": 6.9,
        "people": 45,
        "year": 1996,
        "path": "cover/1996/奥运高手"
    },
    "_6664": {
        "id": "6664",
        "title_cn": "钟楼怪人",
        "title_jp": "The Hunchback of Notre Dame",
        "tips": "1话 /  1996年6月21日 / 加里·特洛斯达勒 / 柯克·维斯",
        "stars": 7.0,
        "people": 42,
        "year": 1996,
        "path": "cover/1996/钟楼怪人"
    },
    "_6681": {
        "id": "6681",
        "title_cn": "剧场版 咕噜咕噜魔法阵",
        "title_jp": "劇場版 魔法陣グルグル",
        "tips": "1话 /  1996-04-20",
        "stars": 7.4,
        "people": 38,
        "year": 1996,
        "path": "cover/1996/剧场版 咕噜咕噜魔法阵"
    },
    "_335": {
        "id": "335",
        "title_cn": "玩具之家",
        "title_jp": "玩具之家",
        "tips": "38话 /  1996年",
        "stars": 6.6,
        "people": 36,
        "year": 1996,
        "path": "cover/1996/玩具之家"
    },
    "_311": {
        "id": "311",
        "title_cn": "热斗小马",
        "title_jp": "みどりのマキバオー",
        "tips": "61话 /  1996年3月2日 / つの丸",
        "stars": 6.7,
        "people": 36,
        "year": 1996,
        "path": "cover/1996/热斗小马"
    },
    "_325": {
        "id": "325",
        "title_cn": "勇者指令",
        "title_jp": "勇者指令ダグオン",
        "tips": "48话 /  1996年2月3日 / 望月智充 / 矢立肇 / オグロアキラ(小黒晃)",
        "stars": 7.0,
        "people": 35,
        "year": 1996,
        "path": "cover/1996/勇者指令"
    },
    "_337": {
        "id": "337",
        "title_cn": "花样男子",
        "title_jp": "花より男子",
        "tips": "51话 /  1996年9月8日 / 神尾葉子",
        "stars": 7.0,
        "people": 34,
        "year": 1996,
        "path": "cover/1996/花样男子"
    },
    "_338": {
        "id": "338",
        "title_cn": "BB有心事",
        "title_jp": "赤ちゃんと僕",
        "tips": "35话 /  1996年7月11日 / 大森貴弘 / 羅川真里茂 / 後藤隆幸",
        "stars": 7.8,
        "people": 30,
        "year": 1996,
        "path": "cover/1996/BB有心事"
    },
    "_6666": {
        "id": "6666",
        "title_cn": "奥美帝III POLY-MATRIX",
        "title_jp": "アミテージ・ザ・サード POLY-MATRIX",
        "tips": "1话 /  1996年4月20日",
        "stars": 6.0,
        "people": 27,
        "year": 1996,
        "path": "cover/1996/奥美帝III POLY-MATRIX"
    },
    "_314": {
        "id": "314",
        "title_cn": "妖精狩猎者",
        "title_jp": "エルフを狩るモノたち",
        "tips": "12话 /  1996年10月3日 / 矢上裕",
        "stars": 6.6,
        "people": 27,
        "year": 1996,
        "path": "cover/1996/妖精狩猎者"
    },
    "_317": {
        "id": "317",
        "title_cn": "城市猎人 秘密任务",
        "title_jp": "シティーハンタースペシャル ザ・シークレット・サービス",
        "tips": "1话 /  1996年1月5日",
        "stars": 6.9,
        "people": 25,
        "year": 1996,
        "path": "cover/1996/城市猎人 秘密任务"
    },
    "_316": {
        "id": "316",
        "title_cn": "鬼太郎第四季",
        "title_jp": "ゲゲゲの鬼太郎",
        "tips": "114话 /  1996年1月7日 / 西尾大介 / 水木しげる / 荒木伸吾、姫野美智",
        "stars": 7.0,
        "people": 25,
        "year": 1996,
        "path": "cover/1996/鬼太郎第四季"
    },
    "_6670": {
        "id": "6670",
        "title_cn": "厕所里的花子",
        "title_jp": "トイレの花子さん",
        "tips": "1话 /  1996年6月29日",
        "stars": 6.1,
        "people": 23,
        "year": 1996,
        "path": "cover/1996/厕所里的花子"
    },
    "_306": {
        "id": "306",
        "title_cn": "酷妹当家",
        "title_jp": "きこちゃんすまいる",
        "tips": "51话 /  1996年10月5日",
        "stars": 7.2,
        "people": 23,
        "year": 1996,
        "path": "cover/1996/酷妹当家"
    },
    "_6671": {
        "id": "6671",
        "title_cn": "开启那扇门",
        "title_jp": "トビラを開けて",
        "tips": "1话 /  1996年",
        "stars": 6.1,
        "people": 22,
        "year": 1996,
        "path": "cover/1996/开启那扇门"
    },
    "_6660": {
        "id": "6660",
        "title_cn": "阿拉丁和大盗之王",
        "title_jp": "Aladdin and the King of Thieves",
        "tips": "1话 /  1996-08-13",
        "stars": 6.4,
        "people": 20,
        "year": 1996,
        "path": "cover/1996/阿拉丁和大盗之王"
    },
    "_302": {
        "id": "302",
        "title_cn": "VS骑士柠檬汽水&40炎",
        "title_jp": "VS騎士ラムネ&40炎",
        "tips": "26话 /  1996年4月3日 / 葦プロ企画室、あかほりさとる（原案）",
        "stars": 7.4,
        "people": 20,
        "year": 1996,
        "path": "cover/1996/VS骑士柠檬汽水&40炎"
    },
    "_299": {
        "id": "299",
        "title_cn": "蜘蛛人 第三季",
        "title_jp": "Spider-Man Season 3 (1996)",
        "tips": "14话 /  1996-04-27",
        "stars": 7.6,
        "people": 20,
        "year": 1996,
        "path": "cover/1996/蜘蛛人 第三季"
    },
    "_330": {
        "id": "330",
        "title_cn": "无家可归的小孩",
        "title_jp": "家なき子レミ",
        "tips": "26话 /  1996年9月1日",
        "stars": 6.9,
        "people": 18,
        "year": 1996,
        "path": "cover/1996/无家可归的小孩"
    },
    "_301": {
        "id": "301",
        "title_cn": "辛普森一家 第八季",
        "title_jp": "The Simpsons Season 8",
        "tips": "25话 /  1996-10-17",
        "stars": 7.3,
        "people": 17,
        "year": 1996,
        "path": "cover/1996/辛普森一家 第八季"
    },
    "_323": {
        "id": "323",
        "title_cn": "巴别塔之书",
        "title_jp": "バベルの本",
        "tips": "1话 /  1996年10月14日",
        "stars": 5.1,
        "people": 16,
        "year": 1996,
        "path": "cover/1996/巴别塔之书"
    },
    "_300": {
        "id": "300",
        "title_cn": "超人",
        "title_jp": "Superman: The Animated Series",
        "tips": "54话 /  1996年9月6日",
        "stars": 7.4,
        "people": 16,
        "year": 1996,
        "path": "cover/1996/超人"
    },
    "_6686": {
        "id": "6686",
        "title_cn": "地狱教师 剧场版",
        "title_jp": "（超）劇場版!地獄先生ぬ〜べ〜",
        "tips": "1话 /  1996年7月6日",
        "stars": 6.8,
        "people": 13,
        "year": 1996,
        "path": "cover/1996/地狱教师 剧场版"
    },
    "_6663": {
        "id": "6663",
        "title_cn": "追寻",
        "title_jp": "Quest",
        "tips": "1话 /  1996年 / Tyron Montgomery / Thomas Stellmach",
        "stars": 5.5,
        "people": 11,
        "year": 1996,
        "path": "cover/1996/追寻"
    },
    "_340": {
        "id": "340",
        "title_cn": "鬼马小精灵",
        "title_jp": "鬼马小精灵",
        "tips": "65话 /  1996年",
        "stars": 7.5,
        "people": 11,
        "year": 1996,
        "path": "cover/1996/鬼马小精灵"
    },
    "_321": {
        "id": "321",
        "title_cn": "魔法提琴手",
        "title_jp": "ハーメルンのバイオリン弾き",
        "tips": "25话 /  1996年10月2日 / 西村純二 / 渡辺道明 / 中嶋敦子",
        "stars": 6.0,
        "people": 10,
        "year": 1996,
        "path": "cover/1996/魔法提琴手"
    },
    "_304": {
        "id": "304",
        "title_cn": "以柔克刚！特别篇 一直对你…。",
        "title_jp": "YAWARA! Special ずっと君のことが…。",
        "tips": "1话 /  1996年7月19日 / 浅香守生 / 浦沢直樹",
        "stars": 7.4,
        "people": 10,
        "year": 1996,
        "path": "cover/1996/以柔克刚！特别篇 一直对你…。"
    },
    "_298": {
        "id": "298",
        "title_cn": "雪儿公主历险记",
        "title_jp": "Princesse Shéhérazade",
        "tips": "52话 /  1996年12月21日",
        "stars": 5.8,
        "people": 10,
        "year": 1996,
        "path": "cover/1996/雪儿公主历险记"
    }
}